treediskpithdetector/__init__.py
treediskpithdetector/cli.py
treediskpithdetector/config.py
treediskpithdetector/detector.py
treediskpithdetector/main.py
treediskpithdetector/detection/__init__.py
treediskpithdetector/detection/detection_method.py
treediskpithdetector/detection/pith_detection.py
treediskpithdetector/geometry/__init__.py
treediskpithdetector/geometry/geometry_utils.py
treediskpithdetector/geometry/line_transformations.py
treediskpithdetector/geometry/primitives.py
treediskpithdetector/geometry/structural_tensor.py
treediskpithdetector/optimization/__init__.py
treediskpithdetector/optimization/least_squares_solver.py
treediskpithdetector/optimization/optimization_utils.py
treediskpithdetector/optimization/optimizer.py
treediskpithdetector/processing/__init__.py
treediskpithdetector/processing/image_processing.py
treediskpithdetector/utils/__init__.py
treediskpithdetector/utils/file_utils.py
treediskpithdetector/visualization/__init__.py
treediskpithdetector/visualization/color.py
treediskpithdetector/visualization/drawing.py
tree_disk_pith_detector-0.1.1.dist-info/METADATA
tree_disk_pith_detector-0.1.1.dist-info/WHEEL
tree_disk_pith_detector-0.1.1.dist-info/entry_points.txt
tree_disk_pith_detector-0.1.1.dist-info/top_level.txt
tree_disk_pith_detector-0.1.1.dist-info/RECORD
