Metadata-Version: 2.1
Name: tree-disk-pith-detector
Version: 0.1.1
Summary: A package for tree disk pith detection in images
Home-page: https://github.com/tuke307/tree-disk-pith-detector
Author: Tony Meissner
Author-email: tonymeissner70@gmail.com
Requires-Python: >=3.7
Requires-Dist: numpy==2.1.2
Requires-Dist: opencv-python==4.10.0.84
Requires-Dist: pandas==2.2.3
Requires-Dist: matplotlib==3.9.2
Requires-Dist: pathlib==1.0.1
Requires-Dist: scikit-learn==1.5.2
Requires-Dist: Pillow==11.0.0
Requires-Dist: scikit-image==0.24.0
Requires-Dist: ultralytics==8.3.23
